simpledate/__init__.py
simpledate-0.0.1.dist-info/LICENCE
simpledate-0.0.1.dist-info/METADATA
simpledate-0.0.1.dist-info/WHEEL
simpledate-0.0.1.dist-info/top_level.txt
simpledate-0.0.1.dist-info/RECORD
